chromepdf/__init__.py
chromepdf/__main__.py
chromepdf/conf.py
chromepdf/exceptions.py
chromepdf/maker.py
chromepdf/pdfconf.py
chromepdf/run.py
chromepdf/shortcuts.py
chromepdf/sizes.py
chromepdf/webdrivermakers.py
chromepdf/webdrivers.py
chromepdf/chromedrivers/blank.txt
chromepdf/chromesession/users/blank.txt
django_chromepdf-1.7.4.dist-info/LICENSE
django_chromepdf-1.7.4.dist-info/METADATA
django_chromepdf-1.7.4.dist-info/WHEEL
django_chromepdf-1.7.4.dist-info/top_level.txt
django_chromepdf-1.7.4.dist-info/RECORD
