Metadata-Version: 2.1
Name: django-chromepdf
Version: 1.7.4
Summary: A small Python 3 library that uses Selenium and Google Chrome to convert HTML into a PDF.
Author-email: Andrew Kukwa <kukwaa@imsweb.com>
Maintainer-email: Andrew Kukwa <kukwaa@imsweb.com>
License: BSD
Project-URL: homepage, https://github.com/imsweb/django-chromepdf
Project-URL: repository, https://github.com/imsweb/django-chromepdf
Project-URL: changelog, https://github.com/imsweb/django-chromepdf/blob/master/CHANGELOG.md
Classifier: Development Status :: 5 - Production/Stable
Classifier: Intended Audience :: Developers
Classifier: License :: OSI Approved :: BSD License
Classifier: Operating System :: POSIX
Classifier: Operating System :: Microsoft :: Windows
Classifier: Operating System :: MacOS :: MacOS X
Classifier: Operating System :: OS Independent
Classifier: Topic :: Utilities
Classifier: Topic :: Software Development :: Libraries
Classifier: Programming Language :: Python
Classifier: Programming Language :: Python :: 3.6
Classifier: Programming Language :: Python :: 3.7
Classifier: Programming Language :: Python :: 3.8
Classifier: Programming Language :: Python :: 3.9
Classifier: Programming Language :: Python :: 3.10
Classifier: Programming Language :: Python :: 3.11
Classifier: Programming Language :: Python :: 3.12
Requires-Python: ~=3.6
License-File: LICENSE
Requires-Dist: selenium<5,>=3
